aws_access_undenied/__init__.py
aws_access_undenied/analysis.py
aws_access_undenied/cli.py
aws_access_undenied/common.py
aws_access_undenied/event.py
aws_access_undenied/event_permission_data.py
aws_access_undenied/iam_policy_data.py
aws_access_undenied/iam_utils.py
aws_access_undenied/organization_node.py
aws_access_undenied/organizations.py
aws_access_undenied/resource_policy_utils.py
aws_access_undenied/result_details.py
aws_access_undenied/results.py
aws_access_undenied/simulate_custom_policy_context_generator.py
aws_access_undenied/simulate_custom_policy_helper.py
aws_access_undenied/simulate_custom_policy_result_analyzer.py
aws_access_undenied/utils.py
aws_access_undenied/definitions/access_denied_message_patterns.json
aws_access_undenied/definitions/map.json
aws_access_undenied-0.1.0.dist-info/LICENSE
aws_access_undenied-0.1.0.dist-info/METADATA
aws_access_undenied-0.1.0.dist-info/NOTICE
aws_access_undenied-0.1.0.dist-info/WHEEL
aws_access_undenied-0.1.0.dist-info/entry_points.txt
aws_access_undenied-0.1.0.dist-info/top_level.txt
aws_access_undenied-0.1.0.dist-info/RECORD
